autoconfiguration/__init__.py
autoconfiguration/autoconfiguration.py
autoconfiguration/create_config.py
autoconfiguration/py.typed
autoconfiguration/exceptions/__init__.py
autoconfiguration/exceptions/base_error.py
autoconfiguration/exceptions/config_class_errors.py
autoconfiguration/exceptions/config_dir_errors.py
autoconfiguration/exceptions/config_file_errors.py
autoconfiguration/exceptions/data_type_errors.py
autoconfiguration/helpers/__init__.py
autoconfiguration/helpers/instances.py
autoconfiguration/helpers/modify_class.py
autoconfiguration-2.3.3.dist-info/LICENSE
autoconfiguration-2.3.3.dist-info/METADATA
autoconfiguration-2.3.3.dist-info/WHEEL
autoconfiguration-2.3.3.dist-info/top_level.txt
autoconfiguration-2.3.3.dist-info/RECORD
