Metadata-Version: 2.1
Name: autoconfiguration
Version: 2.3.3
Summary: Load configuration files (.ini) automatically
Home-page: https://gitlab.com/konstantin-mueller/python-autoconfiguration
Author: Konstantin Müller
Author-email: konstantin.mueller.dev@gmail.com
License: Apache License 2.0
Download-URL: https://gitlab.com/konstantin-mueller/python-autoconfiguration
Project-URL: repository, https://gitlab.com/konstantin-mueller/python-autoconfiguration
Project-URL: bugs, https://gitlab.com/konstantin-mueller/python-autoconfiguration/issues
Platform: UNKNOWN
Classifier: Topic :: Software Development :: Libraries
Classifier: Intended Audience :: Developers
Classifier: License :: OSI Approved :: Apache Software License
Classifier: Operating System :: POSIX
Classifier: Programming Language :: Python
Classifier: Programming Language :: Python :: 3
Classifier: Programming Language :: Python :: 3.8
Classifier: Programming Language :: Python :: 3.9
Classifier: Programming Language :: Python :: 3.10
Classifier: Programming Language :: Python :: 3 :: Only
Requires-Python: >=3.8,<4
License-File: LICENSE
